{"coord": {"lon": 73.8567, "lat": 18.5204}, "list": [{"main": {"aqi": 1}, "components": {"co": 226.97, "no": 0.35, "no2": 4.07, "o3": 31.11, "so2": 2.98, "pm2_5": 2.85, "pm10": 3.91, "nh3": 1.04}, "dt": 1722499200}, {"main": {"aqi": 1}, "components": {"co": 226.97, "no": 0.43, "no2": 4.07, "o3": 31.83, "so2": 3.07, "pm2_5": 3.13, "pm10": 4.2, "nh3": 1.06}, "dt": 1722502800}, {"main": {"aqi": 1}, "components": {"co": 226.97, "no": 0.53, "no2": 4.07, "o3": 31.47, "so2": 2.98, "pm2_5": 3.26, "pm10": 4.44, "nh3": 1.11}, "dt": 1722506400}, {"main": {"aqi": 1}, "components": {"co": 236.99, "no": 0.59, "no2": 5.4, "o3": 28.25, "so2": 3.25, "pm2_5": 3.31, "pm10": 4.59, "nh3": 1.27}, "dt": 1722510000}, {"main": {"aqi": 1}, "components": {"co": 253.68, "no": 0.51, "no2": 7.45, "o3": 23.96, "so2": 3.67, "pm2_5": 3.6, "pm10": 5, "nh3": 1.44}, "dt": 1722513600}, {"main": {"aqi": 1}, "components": {"co": 267.03, "no": 0.17, "no2": 8.91, "o3": 20.74, "so2": 4.17, "pm2_5": 4.02, "pm10": 5.58, "nh3": 1.58}, "dt": 1722517200}, {"main": {"aqi": 1}, "components": {"co": 263.69, "no": 0.07, "no2": 8.14, "o3": 20.74, "so2": 4.23, "pm2_5": 4.26, "pm10": 6.03, "nh3": 1.63}, "dt": 1722520800}, {"main": {"aqi": 1}, "components": {"co": 257.02, "no": 0.05, "no2": 6.94, "o3": 22.17, "so2": 3.99, "pm2_5": 4.04, "pm10": 5.88, "nh3": 1.57}, "dt": 1722524400}, {"main": {"aqi": 1}, "components": {"co": 257.02, "no": 0.04, "no2": 6.43, "o3": 23.25, "so2": 4.11, "pm2_5": 3.98, "pm10": 5.75, "nh3": 1.57}, "dt": 1722528000}, {"main": {"aqi": 1}, "components": {"co": 243.66, "no": 0.03, "no2": 5.65, "o3": 25.03, "so2": 3.73, "pm2_5": 3.62, "pm10": 5.19, "nh3": 1.41}, "dt": 1722531600}, {"main": {"aqi": 1}, "components": {"co": 226.97, "no": 0.02, "no2": 4.76, "o3": 26.82, "so2": 3.1, "pm2_5": 2.84, "pm10": 3.94, "nh3": 1.12}, "dt": 1722535200}, {"main": {"aqi": 1}, "components": {"co": 211.95, "no": 0.01, "no2": 3.6, "o3": 27.89, "so2": 2.53, "pm2_5": 2.32, "pm10": 3.05, "nh3": 0.95}, "dt": 1722538800}, {"main": {"aqi": 1}, "components": {"co": 208.62, "no": 0.01, "no2": 2.91, "o3": 27.89, "so2": 2.35, "pm2_5": 2.3, "pm10": 2.98, "nh3": 0.9}, "dt": 1722542400}, {"main": {"aqi": 1}, "components": {"co": 206.95, "no": 0.01, "no2": 2.44, "o3": 27.54, "so2": 2.24, "pm2_5": 2.63, "pm10": 3.42, "nh3": 0.86}, "dt": 1722546000}, {"main": {"aqi": 1}, "components": {"co": 205.28, "no": 0.01, "no2": 1.99, "o3": 27.54, "so2": 2, "pm2_5": 2.73, "pm10": 3.67, "nh3": 0.82}, "dt": 1722549600}, {"main": {"aqi": 1}, "components": {"co": 205.28, "no": 0.01, "no2": 1.84, "o3": 28.25, "so2": 1.97, "pm2_5": 2.6, "pm10": 3.55, "nh3": 0.8}, "dt": 1722553200}, {"main": {"aqi": 1}, "components": {"co": 206.95, "no": 0.01, "no2": 2.1, "o3": 28.61, "so2": 2.12, "pm2_5": 2.42, "pm10": 3.31, "nh3": 0.82}, "dt": 1722556800}, {"main": {"aqi": 1}, "components": {"co": 216.96, "no": 0.02, "no2": 3, "o3": 27.54, "so2": 2.44, "pm2_5": 2.44, "pm10": 3.38, "nh3": 0.91}, "dt": 1722560400}, {"main": {"aqi": 1}, "components": {"co": 233.65, "no": 0.08, "no2": 4.46, "o3": 25.03, "so2": 2.71, "pm2_5": 2.58, "pm10": 3.77, "nh3": 1.08}, "dt": 1722564000}, {"main": {"aqi": 1}, "components": {"co": 240.33, "no": 0.33, "no2": 4.97, "o3": 24.32, "so2": 2.77, "pm2_5": 2.51, "pm10": 3.78, "nh3": 1.14}, "dt": 1722567600}, {"main": {"aqi": 1}, "components": {"co": 233.65, "no": 0.54, "no2": 4.2, "o3": 25.75, "so2": 2.8, "pm2_5": 2.4, "pm10": 3.64, "nh3": 1.12}, "dt": 1722571200}, {"main": {"aqi": 1}, "components": {"co": 220.3, "no": 0.55, "no2": 3.3, "o3": 28.61, "so2": 2.65, "pm2_5": 2.3, "pm10": 3.44, "nh3": 1.03}, "dt": 1722574800}, {"main": {"aqi": 1}, "components": {"co": 208.62, "no": 0.5, "no2": 2.68, "o3": 31.11, "so2": 2.38, "pm2_5": 2.11, "pm10": 3.1, "nh3": 0.91}, "dt": 1722578400}, {"main": {"aqi": 1}, "components": {"co": 201.94, "no": 0.42, "no2": 2.4, "o3": 32.9, "so2": 2.15, "pm2_5": 2.04, "pm10": 2.94, "nh3": 0.83}, "dt": 1722582000}]}