{"coord": {"lon": 73.8567, "lat": 18.5204}, "list": [{"main": {"aqi": 4}, "components": {"co": 514.03, "no": 0.94, "no2": 6.51, "o3": 134.47, "so2": 14.19, "pm2_5": 59.5, "pm10": 65.27, "nh3": 7.6}, "dt": 1705910400}, {"main": {"aqi": 4}, "components": {"co": 453.95, "no": 0.72, "no2": 5.48, "o3": 134.47, "so2": 11.92, "pm2_5": 50.59, "pm10": 55.73, "nh3": 6.65}, "dt": 1705914000}, {"main": {"aqi": 3}, "components": {"co": 397.21, "no": 0.68, "no2": 5.27, "o3": 124.45, "so2": 9.42, "pm2_5": 38.52, "pm10": 43.03, "nh3": 5.26}, "dt": 1705917600}, {"main": {"aqi": 3}, "components": {"co": 347.14, "no": 0.78, "no2": 6.51, "o3": 113.01, "so2": 9.89, "pm2_5": 24.73, "pm10": 28.03, "nh3": 3.7}, "dt": 1705921200}, {"main": {"aqi": 3}, "components": {"co": 333.79, "no": 0.59, "no2": 8.14, "o3": 104.43, "so2": 9.3, "pm2_5": 22.97, "pm10": 26.04, "nh3": 3.01}, "dt": 1705924800}, {"main": {"aqi": 3}, "components": {"co": 440.6, "no": 0.16, "no2": 16.45, "o3": 82.97, "so2": 7.63, "pm2_5": 34.17, "pm10": 39.94, "nh3": 5.51}, "dt": 1705928400}, {"main": {"aqi": 4}, "components": {"co": 607.49, "no": 0, "no2": 22.28, "o3": 68.66, "so2": 8.7, "pm2_5": 61.57, "pm10": 73.35, "nh3": 9.88}, "dt": 1705932000}, {"main": {"aqi": 5}, "components": {"co": 761.03, "no": 0, "no2": 23.65, "o3": 74.39, "so2": 11.8, "pm2_5": 106.35, "pm10": 124.53, "nh3": 12.67}, "dt": 1705935600}, {"main": {"aqi": 5}, "components": {"co": 974.66, "no": 0, "no2": 27.76, "o3": 70.81, "so2": 15.02, "pm2_5": 153.77, "pm10": 178.33, "nh3": 14.57}, "dt": 1705939200}, {"main": {"aqi": 5}, "components": {"co": 1161.58, "no": 0, "no2": 33.24, "o3": 52.21, "so2": 14.31, "pm2_5": 192.32, "pm10": 222.95, "nh3": 12.67}, "dt": 1705942800}, {"main": {"aqi": 5}, "components": {"co": 1214.98, "no": 0.01, "no2": 35.3, "o3": 37.91, "so2": 11.92, "pm2_5": 220.07, "pm10": 253.27, "nh3": 9.5}, "dt": 1705946400}, {"main": {"aqi": 5}, "components": {"co": 1134.87, "no": 0.01, "no2": 30.5, "o3": 32.9, "so2": 9.54, "pm2_5": 237.34, "pm10": 269.62, "nh3": 8.23}, "dt": 1705950000}, {"main": {"aqi": 5}, "components": {"co": 1108.17, "no": 0.01, "no2": 25.36, "o3": 32.54, "so2": 9.42, "pm2_5": 256.4, "pm10": 287.73, "nh3": 8.04}, "dt": 1705953600}, {"main": {"aqi": 5}, "components": {"co": 1121.52, "no": 0.01, "no2": 22.96, "o3": 30.4, "so2": 9.89, "pm2_5": 275.93, "pm10": 306.94, "nh3": 8.23}, "dt": 1705957200}, {"main": {"aqi": 5}, "components": {"co": 1134.87, "no": 0.01, "no2": 21.59, "o3": 28.25, "so2": 9.78, "pm2_5": 290.86, "pm10": 321.51, "nh3": 8.61}, "dt": 1705960800}, {"main": {"aqi": 5}, "components": {"co": 1134.87, "no": 0.02, "no2": 21.08, "o3": 24.68, "so2": 9.42, "pm2_5": 295.4, "pm10": 325.47, "nh3": 8.61}, "dt": 1705964400}, {"main": {"aqi": 5}, "components": {"co": 1174.93, "no": 0.12, "no2": 23.31, "o3": 18.42, "so2": 9.54, "pm2_5": 293.7, "pm10": 323.46, "nh3": 8.99}, "dt": 1705968000}, {"main": {"aqi": 5}, "components": {"co": 1361.85, "no": 2.18, "no2": 31.53, "o3": 7.15, "so2": 12.04, "pm2_5": 292.84, "pm10": 324.17, "nh3": 10.89}, "dt": 1705971600}, {"main": {"aqi": 5}, "components": {"co": 1815.8, "no": 17.43, "no2": 38.73, "o3": 0.21, "so2": 17.88, "pm2_5": 301.13, "pm10": 337.61, "nh3": 15.58}, "dt": 1705975200}, {"main": {"aqi": 5}, "components": {"co": 2323.15, "no": 45.6, "no2": 40.1, "o3": 1.27, "so2": 23.6, "pm2_5": 309.78, "pm10": 351.5, "nh3": 20.52}, "dt": 1705978800}, {"main": {"aqi": 5}, "components": {"co": 2616.88, "no": 57.22, "no2": 45.24, "o3": 7.33, "so2": 27.66, "pm2_5": 297.16, "pm10": 338.84, "nh3": 23.31}, "dt": 1705982400}, {"main": {"aqi": 5}, "components": {"co": 2349.85, "no": 35.32, "no2": 52.09, "o3": 27.18, "so2": 26.46, "pm2_5": 240.26, "pm10": 275.2, "nh3": 21.53}, "dt": 1705986000}, {"main": {"aqi": 5}, "components": {"co": 1522.06, "no": 10.73, "no2": 36.67, "o3": 79.39, "so2": 23.84, "pm2_5": 161.21, "pm10": 184.38, "nh3": 16.21}, "dt": 1705989600}, {"main": {"aqi": 5}, "components": {"co": 560.76, "no": 1.2, "no2": 7.97, "o3": 131.61, "so2": 17.4, "pm2_5": 85.95, "pm10": 95.87, "nh3": 7.22}, "dt": 1705993200}]}