{"coord": {"lon": 73.8567, "lat": 18.5204}, "list": [{"main": {"aqi": 3}, "components": {"co": 330.45, "no": 0.21, "no2": 3.98, "o3": 128.75, "so2": 8.82, "pm2_5": 28.57, "pm10": 37.8, "nh3": 2.44}, "dt": 1713427200}, {"main": {"aqi": 3}, "components": {"co": 320.43, "no": 0.15, "no2": 4.03, "o3": 124.45, "so2": 8.7, "pm2_5": 27.22, "pm10": 35.82, "nh3": 2.15}, "dt": 1713430800}, {"main": {"aqi": 3}, "components": {"co": 323.77, "no": 0.1, "no2": 4.03, "o3": 127.32, "so2": 9.42, "pm2_5": 28.6, "pm10": 36.78, "nh3": 1.84}, "dt": 1713434400}, {"main": {"aqi": 4}, "components": {"co": 357.15, "no": 0.08, "no2": 5.27, "o3": 141.62, "so2": 12.4, "pm2_5": 31.06, "pm10": 38.28, "nh3": 1.57}, "dt": 1713438000}, {"main": {"aqi": 4}, "components": {"co": 410.56, "no": 0.05, "no2": 7.71, "o3": 160.22, "so2": 19.07, "pm2_5": 39.01, "pm10": 46.81, "nh3": 1.52}, "dt": 1713441600}, {"main": {"aqi": 4}, "components": {"co": 460.62, "no": 0.02, "no2": 11.48, "o3": 157.36, "so2": 24.32, "pm2_5": 47.29, "pm10": 57.89, "nh3": 2.41}, "dt": 1713445200}, {"main": {"aqi": 3}, "components": {"co": 460.62, "no": 0, "no2": 13.71, "o3": 128.75, "so2": 25.03, "pm2_5": 49.36, "pm10": 64.77, "nh3": 3.96}, "dt": 1713448800}, {"main": {"aqi": 3}, "components": {"co": 433.92, "no": 0, "no2": 13.37, "o3": 98.71, "so2": 21.46, "pm2_5": 41.17, "pm10": 58.94, "nh3": 5}, "dt": 1713452400}, {"main": {"aqi": 3}, "components": {"co": 500.68, "no": 0, "no2": 16.79, "o3": 75.82, "so2": 20.03, "pm2_5": 39.32, "pm10": 58.89, "nh3": 7.73}, "dt": 1713456000}, {"main": {"aqi": 3}, "components": {"co": 607.49, "no": 0, "no2": 22.62, "o3": 56.51, "so2": 20.03, "pm2_5": 42.59, "pm10": 64.68, "nh3": 10.89}, "dt": 1713459600}, {"main": {"aqi": 3}, "components": {"co": 634.19, "no": 0, "no2": 26.05, "o3": 44.35, "so2": 19.55, "pm2_5": 43.64, "pm10": 66.17, "nh3": 11.78}, "dt": 1713463200}, {"main": {"aqi": 3}, "components": {"co": 574.11, "no": 0, "no2": 23.31, "o3": 42.2, "so2": 17.88, "pm2_5": 41.58, "pm10": 61.59, "nh3": 11.02}, "dt": 1713466800}, {"main": {"aqi": 3}, "components": {"co": 514.03, "no": 0, "no2": 17.65, "o3": 45.78, "so2": 16.93, "pm2_5": 40.41, "pm10": 57.6, "nh3": 10.51}, "dt": 1713470400}, {"main": {"aqi": 3}, "components": {"co": 480.65, "no": 0, "no2": 13.88, "o3": 47.92, "so2": 16.45, "pm2_5": 40.08, "pm10": 55.08, "nh3": 10.13}, "dt": 1713474000}, {"main": {"aqi": 3}, "components": {"co": 447.27, "no": 0, "no2": 11.65, "o3": 48.64, "so2": 16.21, "pm2_5": 39.32, "pm10": 52.51, "nh3": 9.5}, "dt": 1713477600}, {"main": {"aqi": 3}, "components": {"co": 440.6, "no": 0, "no2": 11.31, "o3": 47.21, "so2": 15.74, "pm2_5": 38.62, "pm10": 50.34, "nh3": 8.99}, "dt": 1713481200}, {"main": {"aqi": 3}, "components": {"co": 440.6, "no": 0, "no2": 11.82, "o3": 47.21, "so2": 14.78, "pm2_5": 37.4, "pm10": 48.04, "nh3": 8.87}, "dt": 1713484800}, {"main": {"aqi": 3}, "components": {"co": 487.33, "no": 0, "no2": 15.42, "o3": 45.06, "so2": 13.95, "pm2_5": 36.53, "pm10": 47.2, "nh3": 9.37}, "dt": 1713488400}, {"main": {"aqi": 3}, "components": {"co": 587.46, "no": 0.26, "no2": 22.96, "o3": 40.05, "so2": 13.83, "pm2_5": 35.7, "pm10": 47.63, "nh3": 10.01}, "dt": 1713492000}, {"main": {"aqi": 3}, "components": {"co": 600.81, "no": 1.65, "no2": 23.99, "o3": 48.64, "so2": 12.52, "pm2_5": 31.61, "pm10": 43.4, "nh3": 8.61}, "dt": 1713495600}, {"main": {"aqi": 3}, "components": {"co": 453.95, "no": 1.24, "no2": 13.71, "o3": 80.82, "so2": 11.09, "pm2_5": 26.02, "pm10": 34.97, "nh3": 5.38}, "dt": 1713499200}, {"main": {"aqi": 3}, "components": {"co": 423.91, "no": 0.92, "no2": 11.14, "o3": 98.71, "so2": 10.97, "pm2_5": 26.22, "pm10": 35.53, "nh3": 5.26}, "dt": 1713502800}, {"main": {"aqi": 3}, "components": {"co": 403.88, "no": 0.61, "no2": 8.65, "o3": 115.87, "so2": 10.01, "pm2_5": 26.61, "pm10": 36.62, "nh3": 5.32}, "dt": 1713506400}, {"main": {"aqi": 3}, "components": {"co": 340.46, "no": 0.17, "no2": 4.67, "o3": 114.44, "so2": 6.26, "pm2_5": 23.34, "pm10": 31.69, "nh3": 3.36}, "dt": 1713510000}]}