{"coord": {"lon": 73.8567, "lat": 18.5204}, "list": [{"main": {"aqi": 4}, "components": {"co": 360.49, "no": 0.4, "no2": 3.51, "o3": 147.34, "so2": 12.87, "pm2_5": 43.38, "pm10": 51.66, "nh3": 4.75}, "dt": 1698566400}, {"main": {"aqi": 4}, "components": {"co": 357.15, "no": 0.4, "no2": 3.81, "o3": 147.34, "so2": 12.64, "pm2_5": 43.49, "pm10": 51.69, "nh3": 4.37}, "dt": 1698570000}, {"main": {"aqi": 3}, "components": {"co": 467.3, "no": 1.08, "no2": 10.88, "o3": 131.61, "so2": 14.66, "pm2_5": 48.72, "pm10": 57.9, "nh3": 6.08}, "dt": 1698573600}, {"main": {"aqi": 4}, "components": {"co": 647.54, "no": 1.68, "no2": 22.96, "o3": 108.72, "so2": 17.17, "pm2_5": 56.26, "pm10": 67.2, "nh3": 8.61}, "dt": 1698577200}, {"main": {"aqi": 4}, "components": {"co": 801.09, "no": 0.89, "no2": 35.99, "o3": 82.25, "so2": 18.12, "pm2_5": 60.24, "pm10": 72.57, "nh3": 10.64}, "dt": 1698580800}, {"main": {"aqi": 4}, "components": {"co": 907.9, "no": 0.02, "no2": 41.47, "o3": 58.65, "so2": 18.12, "pm2_5": 62.72, "pm10": 77.03, "nh3": 13.43}, "dt": 1698584400}, {"main": {"aqi": 4}, "components": {"co": 1068.12, "no": 0, "no2": 44.55, "o3": 37.91, "so2": 20.03, "pm2_5": 70.25, "pm10": 88.81, "nh3": 19.25}, "dt": 1698588000}, {"main": {"aqi": 5}, "components": {"co": 1214.98, "no": 0.05, "no2": 48.67, "o3": 22.53, "so2": 22.65, "pm2_5": 78.87, "pm10": 102.21, "nh3": 26.09}, "dt": 1698591600}, {"main": {"aqi": 5}, "components": {"co": 1335.14, "no": 0.11, "no2": 47.98, "o3": 17.7, "so2": 25.99, "pm2_5": 88.09, "pm10": 115.38, "nh3": 32.93}, "dt": 1698595200}, {"main": {"aqi": 5}, "components": {"co": 1375.2, "no": 0.05, "no2": 44.55, "o3": 21.28, "so2": 25.51, "pm2_5": 95.31, "pm10": 123.99, "nh3": 34.45}, "dt": 1698598800}, {"main": {"aqi": 5}, "components": {"co": 1281.74, "no": 0.01, "no2": 40.44, "o3": 26.82, "so2": 21.22, "pm2_5": 93.79, "pm10": 120.9, "nh3": 33.44}, "dt": 1698602400}, {"main": {"aqi": 5}, "components": {"co": 1094.82, "no": 0, "no2": 34.96, "o3": 30.04, "so2": 15.26, "pm2_5": 82.51, "pm10": 104.8, "nh3": 28.63}, "dt": 1698606000}, {"main": {"aqi": 5}, "components": {"co": 988.01, "no": 0.01, "no2": 30.85, "o3": 24.32, "so2": 13.11, "pm2_5": 77.06, "pm10": 97.07, "nh3": 25.84}, "dt": 1698609600}, {"main": {"aqi": 4}, "components": {"co": 921.25, "no": 0.02, "no2": 26.73, "o3": 19.85, "so2": 13.11, "pm2_5": 73.85, "pm10": 93.15, "nh3": 27.11}, "dt": 1698613200}, {"main": {"aqi": 4}, "components": {"co": 867.84, "no": 0.05, "no2": 24.68, "o3": 16.63, "so2": 14.07, "pm2_5": 72.71, "pm10": 92.88, "nh3": 31.92}, "dt": 1698616800}, {"main": {"aqi": 4}, "components": {"co": 867.84, "no": 0.14, "no2": 23.65, "o3": 12.7, "so2": 13.95, "pm2_5": 73.63, "pm10": 94.3, "nh3": 32.93}, "dt": 1698620400}, {"main": {"aqi": 5}, "components": {"co": 921.25, "no": 0.57, "no2": 24.68, "o3": 7.78, "so2": 13.95, "pm2_5": 77.02, "pm10": 97.25, "nh3": 30.15}, "dt": 1698624000}, {"main": {"aqi": 5}, "components": {"co": 1068.12, "no": 4.14, "no2": 28.79, "o3": 2.32, "so2": 18.36, "pm2_5": 83.82, "pm10": 105.04, "nh3": 32.17}, "dt": 1698627600}, {"main": {"aqi": 5}, "components": {"co": 1535.42, "no": 21.01, "no2": 34.96, "o3": 0.35, "so2": 31.47, "pm2_5": 103.75, "pm10": 130.41, "nh3": 44.58}, "dt": 1698631200}, {"main": {"aqi": 5}, "components": {"co": 2189.64, "no": 50.51, "no2": 42.5, "o3": 3.67, "so2": 47.21, "pm2_5": 131.84, "pm10": 165.37, "nh3": 60.29}, "dt": 1698634800}, {"main": {"aqi": 5}, "components": {"co": 2590.18, "no": 54.99, "no2": 63.75, "o3": 15.02, "so2": 60.56, "pm2_5": 154.76, "pm10": 189.74, "nh3": 66.88}, "dt": 1698638400}, {"main": {"aqi": 5}, "components": {"co": 2216.34, "no": 23.92, "no2": 74.71, "o3": 61.51, "so2": 59.6, "pm2_5": 151.76, "pm10": 179.44, "nh3": 52.18}, "dt": 1698642000}, {"main": {"aqi": 5}, "components": {"co": 1361.85, "no": 6.09, "no2": 40.1, "o3": 134.47, "so2": 42.44, "pm2_5": 116.98, "pm10": 134.07, "nh3": 28.12}, "dt": 1698645600}, {"main": {"aqi": 4}, "components": {"co": 453.95, "no": 0.68, "no2": 5.91, "o3": 151.63, "so2": 16.93, "pm2_5": 56.98, "pm10": 64.5, "nh3": 7.28}, "dt": 1698649200}]}