{"coord": {"lon": 73.8567, "lat": 18.5204}, "list": [{"main": {"aqi": 3}, "components": {"co": 467.3, "no": 0.31, "no2": 4.03, "o3": 138.76, "so2": 8.11, "pm2_5": 16.74, "pm10": 19.12, "nh3": 3.93}, "dt": 1715846400}, {"main": {"aqi": 3}, "components": {"co": 453.95, "no": 0.28, "no2": 4.24, "o3": 134.47, "so2": 7.27, "pm2_5": 16.03, "pm10": 18.41, "nh3": 3.61}, "dt": 1715850000}, {"main": {"aqi": 3}, "components": {"co": 440.6, "no": 0.24, "no2": 4.5, "o3": 128.75, "so2": 6.14, "pm2_5": 15.05, "pm10": 17.38, "nh3": 3.39}, "dt": 1715853600}, {"main": {"aqi": 3}, "components": {"co": 440.6, "no": 0.21, "no2": 4.93, "o3": 125.89, "so2": 4.95, "pm2_5": 14.21, "pm10": 16.55, "nh3": 3.42}, "dt": 1715857200}, {"main": {"aqi": 3}, "components": {"co": 440.6, "no": 0.14, "no2": 5.01, "o3": 123.02, "so2": 3.76, "pm2_5": 14.38, "pm10": 16.92, "nh3": 3.64}, "dt": 1715860800}, {"main": {"aqi": 3}, "components": {"co": 500.68, "no": 0.07, "no2": 8.74, "o3": 120.16, "so2": 5.9, "pm2_5": 22.01, "pm10": 26.08, "nh3": 5.07}, "dt": 1715864400}, {"main": {"aqi": 3}, "components": {"co": 620.84, "no": 0, "no2": 14.74, "o3": 113.01, "so2": 10.85, "pm2_5": 36.17, "pm10": 43.44, "nh3": 7.41}, "dt": 1715868000}, {"main": {"aqi": 3}, "components": {"co": 714.3, "no": 0, "no2": 18.68, "o3": 110.15, "so2": 14.9, "pm2_5": 48.3, "pm10": 59.07, "nh3": 9.63}, "dt": 1715871600}, {"main": {"aqi": 4}, "components": {"co": 974.66, "no": 0, "no2": 29.82, "o3": 82.25, "so2": 19.31, "pm2_5": 63.34, "pm10": 80.45, "nh3": 15.83}, "dt": 1715875200}, {"main": {"aqi": 5}, "components": {"co": 1281.74, "no": 0, "no2": 42.5, "o3": 43.27, "so2": 20.74, "pm2_5": 80.84, "pm10": 106.06, "nh3": 21.28}, "dt": 1715878800}, {"main": {"aqi": 5}, "components": {"co": 1335.14, "no": 0.07, "no2": 44.55, "o3": 19.67, "so2": 17.17, "pm2_5": 87.4, "pm10": 116.4, "nh3": 21.28}, "dt": 1715882400}, {"main": {"aqi": 5}, "components": {"co": 1148.22, "no": 0.18, "no2": 35.64, "o3": 12.7, "so2": 12.28, "pm2_5": 81.23, "pm10": 109.59, "nh3": 18.49}, "dt": 1715886000}, {"main": {"aqi": 5}, "components": {"co": 988.01, "no": 0.12, "no2": 27.42, "o3": 12.87, "so2": 11.09, "pm2_5": 75.78, "pm10": 103.42, "nh3": 17.48}, "dt": 1715889600}, {"main": {"aqi": 4}, "components": {"co": 921.25, "no": 0.09, "no2": 24.33, "o3": 13.05, "so2": 12.16, "pm2_5": 74.64, "pm10": 102.68, "nh3": 19.51}, "dt": 1715893200}, {"main": {"aqi": 4}, "components": {"co": 847.82, "no": 0.06, "no2": 21.08, "o3": 14.31, "so2": 12.87, "pm2_5": 71.64, "pm10": 99.59, "nh3": 21.79}, "dt": 1715896800}, {"main": {"aqi": 4}, "components": {"co": 747.68, "no": 0.06, "no2": 17.48, "o3": 15.38, "so2": 11.32, "pm2_5": 66.06, "pm10": 93.25, "nh3": 18.75}, "dt": 1715900400}, {"main": {"aqi": 4}, "components": {"co": 694.27, "no": 0.16, "no2": 16.96, "o3": 13.41, "so2": 10.01, "pm2_5": 61.2, "pm10": 87.5, "nh3": 14.69}, "dt": 1715904000}, {"main": {"aqi": 4}, "components": {"co": 794.41, "no": 2.32, "no2": 21.42, "o3": 5.23, "so2": 10.49, "pm2_5": 62.28, "pm10": 90.34, "nh3": 13.43}, "dt": 1715907600}, {"main": {"aqi": 4}, "components": {"co": 988.01, "no": 13.52, "no2": 21.42, "o3": 2.64, "so2": 12.04, "pm2_5": 64.58, "pm10": 97.73, "nh3": 14.69}, "dt": 1715911200}, {"main": {"aqi": 4}, "components": {"co": 988.01, "no": 21.01, "no2": 20.91, "o3": 9.3, "so2": 11.21, "pm2_5": 57.14, "pm10": 94.65, "nh3": 13.3}, "dt": 1715914800}, {"main": {"aqi": 3}, "components": {"co": 447.27, "no": 0.79, "no2": 6.25, "o3": 103, "so2": 6.5, "pm2_5": 27.18, "pm10": 40.71, "nh3": 3.93}, "dt": 1715918400}, {"main": {"aqi": 3}, "components": {"co": 423.91, "no": 0.34, "no2": 3.13, "o3": 121.59, "so2": 5.3, "pm2_5": 24.91, "pm10": 33.43, "nh3": 3.7}, "dt": 1715922000}, {"main": {"aqi": 3}, "components": {"co": 407.22, "no": 0.27, "no2": 2.59, "o3": 128.75, "so2": 5.54, "pm2_5": 27.84, "pm10": 37.01, "nh3": 3.67}, "dt": 1715925600}, {"main": {"aqi": 3}, "components": {"co": 400.54, "no": 0.24, "no2": 2.55, "o3": 131.61, "so2": 6.02, "pm2_5": 30.88, "pm10": 40.59, "nh3": 3.61}, "dt": 1715929200}]}